{"0": "Achievements", "1": "Admission", "2": "Admission Documents", "3": "Clubs", "4": "College statistics", "5": "Day-scholar", "6": "Faculty", "7": "Higher studies training", "8": "Hosteller", "9": "Lateral Entry", "10": "Placement", "11": "Seats", "12": "Sports_Quota", "13": "Syllabus", "14": "Transportation", "15": "affirm", "16": "bme_course", "17": "bot_challenge", "18": "civil_course", "19": "code_of_conduct", "20": "contact", "21": "councelling_quota", "22": "course_fee", "23": "cse_course", "24": "cutoff", "25": "deny", "26": "ece_course", "27": "eee_course", "28": "enrollment_strength", "29": "facilities_differ", "30": "faculties_list", "31": "founder_date", "32": "goodbye", "33": "greet", "34": "high_package", "35": "hostel_enroll", "36": "infrastructure", "37": "it_course", "38": "lateral_eligible", "39": "library", "40": "management_quota", "41": "marking_system", "42": "mech_course", "43": "mood_great", "44": "mood_unhappy", "45": "pg_courses", "46": "phd_staff", "47": "ranking", "48": "ranking_tn", "49": "scholarship", "50": "sports_facilities", "51": "ug_courses_available", "52": "vision"}